mlx_boosting/__init__.py
mlx_boosting/base.py
mlx_boosting/gbdt.py
mlx_boosting/py.typed
mlx_boosting/xgboost.py
mlx_boosting/losses/__init__.py
mlx_boosting/losses/classification.py
mlx_boosting/losses/regression.py
mlx_boosting/trees/__init__.py
mlx_boosting/trees/_fast_builder.py
mlx_boosting/trees/_numba_builder.py
mlx_boosting/trees/_numpy_builder.py
mlx_boosting/trees/_predictor.py
mlx_boosting/trees/_split_finder.py
mlx_boosting/trees/_tree_builder.py
mlx_boosting/trees/_tree_structure.py
mlx_boosting/trees/decision_tree.py
mlx_boosting/utils/__init__.py
mlx_boosting/utils/data.py
mlx_boosting/utils/metrics.py
mlx_boosting-1.0.0.dist-info/METADATA
mlx_boosting-1.0.0.dist-info/WHEEL
mlx_boosting-1.0.0.dist-info/licenses/LICENSE
mlx_boosting-1.0.0.dist-info/RECORD
