Metadata-Version: 2.4
Name: mlx-boosting
Version: 1.0.0
Summary: GPU-accelerated boosting algorithms using Apple MLX for Apple Silicon
Project-URL: Homepage, https://github.com/qnguyen3/mlx-boosting
Project-URL: Repository, https://github.com/qnguyen3/mlx-boosting
Project-URL: Documentation, https://github.com/qnguyen3/mlx-boosting#readme
Project-URL: Issues, https://github.com/qnguyen3/mlx-boosting/issues
Project-URL: Changelog, https://github.com/qnguyen3/mlx-boosting/releases
Author: Quan Nguyen
License-Expression: MIT
License-File: LICENSE
Keywords: apple-silicon,boosting,gbdt,gpu,gradient-boosting,m1,m2,m3,machine-learning,mlx,xgboost
Classifier: Development Status :: 4 - Beta
Classifier: Intended Audience :: Developers
Classifier: Intended Audience :: Science/Research
Classifier: License :: OSI Approved :: MIT License
Classifier: Operating System :: MacOS
Classifier: Programming Language :: Python :: 3
Classifier: Programming Language :: Python :: 3.10
Classifier: Programming Language :: Python :: 3.11
Classifier: Programming Language :: Python :: 3.12
Classifier: Programming Language :: Python :: 3.13
Classifier: Topic :: Scientific/Engineering :: Artificial Intelligence
Requires-Python: >=3.10
Requires-Dist: mlx>=0.10.0
Requires-Dist: numba>=0.63.1
Requires-Dist: numpy>=1.24.0
Requires-Dist: scikit-learn>=1.7.2
Provides-Extra: dev
Requires-Dist: mypy>=1.9.0; extra == 'dev'
Requires-Dist: pre-commit>=3.0.0; extra == 'dev'
Requires-Dist: pytest-cov>=4.0.0; extra == 'dev'
Requires-Dist: pytest>=8.0.0; extra == 'dev'
Requires-Dist: ruff>=0.4.0; extra == 'dev'
